[
  {
    "login": "Jinyong-Li",
    "id": 209943074,
    "node_id": "U_kgDODIN6Ig",
    "avatar_url": "https://avatars.githubusercontent.com/u/209943074?v=4",
    "gravatar_id": "",
    "url": "https://api.github.com/users/Jinyong-Li",
    "html_url": "https://github.com/Jinyong-Li",
    "followers_url": "https://api.github.com/users/Jinyong-Li/followers",
    "following_url": "https://api.github.com/users/Jinyong-Li/following{/other_user}",
    "gists_url": "https://api.github.com/users/Jinyong-Li/gists{/gist_id}",
    "starred_url": "https://api.github.com/users/Jinyong-Li/starred{/owner}{/repo}",
    "subscriptions_url": "https://api.github.com/users/Jinyong-Li/subscriptions",
    "organizations_url": "https://api.github.com/users/Jinyong-Li/orgs",
    "repos_url": "https://api.github.com/users/Jinyong-Li/repos",
    "events_url": "https://api.github.com/users/Jinyong-Li/events{/privacy}",
    "received_events_url": "https://api.github.com/users/Jinyong-Li/received_events",
    "type": "User",
    "user_view_type": "public",
    "site_admin": false,
    "contributions": 59
  },
  {
    "login": "github-actions[bot]",
    "id": 41898282,
    "node_id": "MDM6Qm90NDE4OTgyODI=",
    "avatar_url": "https://avatars.githubusercontent.com/in/15368?v=4",
    "gravatar_id": "",
    "url": "https://api.github.com/users/github-actions%5Bbot%5D",
    "html_url": "https://github.com/apps/github-actions",
    "followers_url": "https://api.github.com/users/github-actions%5Bbot%5D/followers",
    "following_url": "https://api.github.com/users/github-actions%5Bbot%5D/following{/other_user}",
    "gists_url": "https://api.github.com/users/github-actions%5Bbot%5D/gists{/gist_id}",
    "starred_url": "https://api.github.com/users/github-actions%5Bbot%5D/starred{/owner}{/repo}",
    "subscriptions_url": "https://api.github.com/users/github-actions%5Bbot%5D/subscriptions",
    "organizations_url": "https://api.github.com/users/github-actions%5Bbot%5D/orgs",
    "repos_url": "https://api.github.com/users/github-actions%5Bbot%5D/repos",
    "events_url": "https://api.github.com/users/github-actions%5Bbot%5D/events{/privacy}",
    "received_events_url": "https://api.github.com/users/github-actions%5Bbot%5D/received_events",
    "type": "Bot",
    "user_view_type": "public",
    "site_admin": false,
    "contributions": 6
  },
  {
    "login": "yrz-bot",
    "id": 199222741,
    "node_id": "U_kgDOC9_l1Q",
    "avatar_url": "https://avatars.githubusercontent.com/u/199222741?v=4",
    "gravatar_id": "",
    "url": "https://api.github.com/users/yrz-bot",
    "html_url": "https://github.com/yrz-bot",
    "followers_url": "https://api.github.com/users/yrz-bot/followers",
    "following_url": "https://api.github.com/users/yrz-bot/following{/other_user}",
    "gists_url": "https://api.github.com/users/yrz-bot/gists{/gist_id}",
    "starred_url": "https://api.github.com/users/yrz-bot/starred{/owner}{/repo}",
    "subscriptions_url": "https://api.github.com/users/yrz-bot/subscriptions",
    "organizations_url": "https://api.github.com/users/yrz-bot/orgs",
    "repos_url": "https://api.github.com/users/yrz-bot/repos",
    "events_url": "https://api.github.com/users/yrz-bot/events{/privacy}",
    "received_events_url": "https://api.github.com/users/yrz-bot/received_events",
    "type": "User",
    "user_view_type": "public",
    "site_admin": false,
    "contributions": 1
  }
]
